README.md
pyproject.toml
setup.py
mongoengine_migrate/__init__.py
mongoengine_migrate/cli.py
mongoengine_migrate/db_manager.py
mongoengine_migrate/exceptions.py
mongoengine_migrate/flags.py
mongoengine_migrate/graph.py
mongoengine_migrate/loader.py
mongoengine_migrate/migration_template.tpl
mongoengine_migrate/mongo.py
mongoengine_migrate/query_tracer.py
mongoengine_migrate/schema.py
mongoengine_migrate/updater.py
mongoengine_migrate/utils.py
mongoengine_migrate.egg-info/PKG-INFO
mongoengine_migrate.egg-info/SOURCES.txt
mongoengine_migrate.egg-info/dependency_links.txt
mongoengine_migrate.egg-info/entry_points.txt
mongoengine_migrate.egg-info/requires.txt
mongoengine_migrate.egg-info/top_level.txt
mongoengine_migrate/actions/__init__.py
mongoengine_migrate/actions/base.py
mongoengine_migrate/actions/document.py
mongoengine_migrate/actions/embedded.py
mongoengine_migrate/actions/factory.py
mongoengine_migrate/actions/fields.py
mongoengine_migrate/actions/index.py
mongoengine_migrate/actions/run_python.py
mongoengine_migrate/fields/__init__.py
mongoengine_migrate/fields/base.py
mongoengine_migrate/fields/common.py
mongoengine_migrate/fields/registry.py
mongoengine_migrate/fields/converters/__init__.py
mongoengine_migrate/fields/converters/common.py
mongoengine_migrate/fields/converters/geo.py
tests/action/__init__.py
tests/action/test_actions_rank.py
tests/action/test_alter_document.py
tests/action/test_alter_embedded.py
tests/action/test_alter_field.py
tests/action/test_alter_index.py
tests/action/test_base_action.py
tests/action/test_create_document.py
tests/action/test_create_embedded.py
tests/action/test_create_field.py
tests/action/test_create_index.py
tests/action/test_drop_document.py
tests/action/test_drop_embedded.py
tests/action/test_drop_field.py
tests/action/test_drop_index.py
tests/action/test_rename_document.py
tests/action/test_rename_embedded.py
tests/action/test_rename_field.py
tests/action/test_run_python.py
tests/fixtures/__init__.py
tests/fixtures/schema1.py