Metadata-Version: 2.1
Name: mongoengine-migrate
Version: 0.0.3
Summary: Migrations for MongoEngine ODM inspired by Django
Home-page: https://github.com/bdragon300/mongoengine-migrate
Author: Igor Derkach
Author-email: gosha753951@gmail.com
License: Apache-2.0
Keywords: mongo,mongodb,mongoengine,migrate,migration
Platform: UNKNOWN
Classifier: Programming Language :: Python :: 3.6
Classifier: Programming Language :: Python :: 3.7
Classifier: Programming Language :: Python :: 3.8
Classifier: Development Status :: 3 - Alpha
Classifier: License :: OSI Approved :: Apache Software License
Classifier: Intended Audience :: Developers
Classifier: Topic :: Database
Requires-Python: >=3.6
